nonebot_plugin_wife/__init__.py
nonebot_plugin_wife/resource/琪露诺
nonebot_plugin_wife-0.0.3.dist-info/LICENSE
nonebot_plugin_wife-0.0.3.dist-info/METADATA
nonebot_plugin_wife-0.0.3.dist-info/WHEEL
nonebot_plugin_wife-0.0.3.dist-info/RECORD
