Metadata-Version: 2.1
Name: nonebot-plugin-wife
Version: 0.0.3
Summary: 每日随机二次元wife in NoneBot2
Home-page: https://github.com/tkgs0/nonebot-plugin-wife
License: MIT
Keywords: nonebot,wife
Author: 月ヶ瀬
Requires-Python: >=3.9,<4.0
Classifier: License :: OSI Approved :: MIT License
Classifier: Programming Language :: Python :: 3
Classifier: Programming Language :: Python :: 3.9
Classifier: Programming Language :: Python :: 3.10
Classifier: Programming Language :: Python :: 3.11
Classifier: Programming Language :: Python :: 3.12
Classifier: Programming Language :: Python :: 3.13
Requires-Dist: httpx (>=0.25.0)
Requires-Dist: nonebot-adapter-onebot (>=2.4.1,<3.0.0)
Requires-Dist: nonebot-plugin-localstore (>=0.7.1,<0.8.0)
Requires-Dist: nonebot2 (>=2.3.1,<3.0.0)
Requires-Dist: ujson (>=5.2.0)
Project-URL: Repository, https://github.com/tkgs0/nonebot-plugin-wife
